ipycallback/__init__.py
ipycallback/_frontend.py
ipycallback/_version.py
ipycallback/slow_js_callback.py
ipycallback/slow_tunnel.py
ipycallback/labextension/ipycallback-0.1.0.tgz
ipycallback/labextension/ipycallback-0.2.1.tgz
ipycallback/labextension/ipycallback-0.2.2.tgz
ipycallback/labextension/ipycallback-0.2.4.tgz
ipycallback/labextension/ipycallback-0.2.5.tgz
ipycallback/nbextension/__init__.py
ipycallback/nbextension/static/extension.js
ipycallback/nbextension/static/index.js
ipycallback/nbextension/static/index.js.map
ipycallback/tests/__init__.py
ipycallback/tests/conftest.py
ipycallback/tests/test_example.py
ipycallback/tests/test_nbextension_path.py
ipycallback-0.2.5.data/data/etc/jupyter/nbconfig/notebook.d/ipycallback.json
ipycallback-0.2.5.data/data/share/jupyter/lab/extensions/ipycallback-0.2.5.tgz
ipycallback-0.2.5.data/data/share/jupyter/nbextensions/ipycallback/extension.js
ipycallback-0.2.5.data/data/share/jupyter/nbextensions/ipycallback/index.js
ipycallback-0.2.5.data/data/share/jupyter/nbextensions/ipycallback/index.js.map
ipycallback-0.2.5.dist-info/LICENSE.txt
ipycallback-0.2.5.dist-info/METADATA
ipycallback-0.2.5.dist-info/WHEEL
ipycallback-0.2.5.dist-info/top_level.txt
ipycallback-0.2.5.dist-info/RECORD
